cert_manager_plugin/__init__.py
cert_manager_plugin/consts.py
cert_manager_plugin/plugin.py
cert_manager_plugin/assets/acme-synopsis.md
cert_manager_plugin/assets/choose-issuer-synopsis.md
cert_manager_plugin/assets/create-issuer-synopsis.md
cert_manager_plugin/descriptors/operation/create/operation.yaml
cert_manager_plugin/descriptors/variables/issuer-type-variable.yaml
cert_manager_plugin/descriptors/variables/issuer-variables.yaml
cert_manager_plugin/descriptors/view_spec/small_issuer_specs.yaml
cert_manager_plugin-0.0.8.dist-info/METADATA
cert_manager_plugin-0.0.8.dist-info/WHEEL
cert_manager_plugin-0.0.8.dist-info/top_level.txt
cert_manager_plugin-0.0.8.dist-info/RECORD
